informationGain/__init__.py
informationGain/main.py
informationgain-3.0.0.dist-info/METADATA
informationgain-3.0.0.dist-info/WHEEL
informationgain-3.0.0.dist-info/top_level.txt
informationgain-3.0.0.dist-info/RECORD
