Metadata-Version: 2.4
Name: InformationGain
Version: 3.0.0
Summary: A Python package for calculating information gain.
Home-page: https://github.com/AbhinavMsh/informationGain
Author: Abhinav Masih
Author-email: abhnv.msh@gmail.com
Classifier: Programming Language :: Python :: 3
Classifier: License :: OSI Approved :: MIT License
Classifier: Operating System :: OS Independent
Requires-Python: >=3.12
Dynamic: author
Dynamic: author-email
Dynamic: classifier
Dynamic: description
Dynamic: description-content-type
Dynamic: home-page
Dynamic: requires-python
Dynamic: summary
